{
  "proton-mail": [
    "common-5.patch",
    "drop-circular-dependency-2.patch",
    "url-6.patch",
    "constants-10.patch",
    "sentry-16.patch",
    "pack-api-arg-5.patch",
    "pack-webpack-8.patch",
    "session-storage-5.patch",
    "link-handler-7.patch",
    "embedded-verification-3.patch",
    "proton-mail.patch"
  ],
  "proton-account": [
    "common-7.patch",
    "drop-circular-dependency-2.patch",
    "url-6.patch",
    "constants-10.patch",
    "sentry-16.patch",
    "pack-api-arg-5.patch",
    "pack-webpack-9.patch",
    "session-storage-5.patch",
    "link-handler-7.patch",
    "embedded-verification-3.patch",
    "proton-account.patch"
  ],
  "proton-calendar": [
    "common-5.patch",
    "drop-circular-dependency-2.patch",
    "url-6.patch",
    "constants-10.patch",
    "sentry-16.patch",
    "pack-api-arg-5.patch",
    "pack-webpack-8.patch",
    "session-storage-5.patch",
    "link-handler-7.patch",
    "embedded-verification-3.patch",
    "proton-calendar.patch"
  ],
  "proton-drive": [
    "common-6.patch",
    "drop-circular-dependency-2.patch",
    "url-6.patch",
    "constants-10.patch",
    "sentry-15.patch",
    "pack-api-arg-5.patch",
    "pack-webpack-8.patch",
    "session-storage-5.patch",
    "link-handler-7.patch",
    "embedded-verification-3.patch",
    "proton-drive.patch"
  ],
  "proton-vpn-settings": [
    "common-7.patch",
    "drop-circular-dependency-2.patch",
    "url-6.patch",
    "constants-10.patch",
    "sentry-16.patch",
    "pack-api-arg-5.patch",
    "pack-webpack-9.patch",
    "session-storage-5.patch",
    "link-handler-7.patch",
    "embedded-verification-3.patch",
    "proton-vpn-settings.patch"
  ]
}
